MANIFEST.in
README.md
setup.py
django_ytindex.egg-info/PKG-INFO
django_ytindex.egg-info/SOURCES.txt
django_ytindex.egg-info/dependency_links.txt
django_ytindex.egg-info/requires.txt
django_ytindex.egg-info/top_level.txt
ytindex/__init__.py
ytindex/admin.py
ytindex/apps.py
ytindex/models.py
ytindex/urls.py
ytindex/views.py
ytindex/indexing/__init__.py
ytindex/indexing/downloader.py
ytindex/indexing/esindex.py
ytindex/indexing/golden_q.py
ytindex/indexing/ytapi.py
ytindex/indexing/ytcaptions.py
ytindex/management/commands/index_latest.py
ytindex/management/commands/index_playlist.py